VnCcode/characterBitCount.v
/*
Bryan Bednarski
EE 371 Prof. Peckol Winter 2016
Project 3: Extending a Microprocessor

characterBitCount.v
This verilog module combines the functionality of the Bit Identification Count, 
Bit Sample Count and S/R Clock Control top-level modules
*/

module characterBitCount(charReceived, SRclk, BIC, BSC, clk, reset, bitStream, enable);
	output reg charReceived, SRclk;
	output reg [3:0] BIC, BSC;
	input clk, reset, bitStream, enable;
	
	reg [7:0] combinedCounter;
	
	initial
		begin
			BIC = 4'b0;
			BSC = 4'b0;
			combinedCounter = 8'b0;
			charReceived = 1'b0;
			SRclk = 1'b0;
		end
	
	//BIC[3:0] = combinedCounter[7:4];
	//BSC[3:0] = combinedCounter[3:0];
	
	// assign BIC = 4'b0;
	// assign BSC = 4'b0;
	
	always@(posedge clk)
		begin
			BIC[3:0] = combinedCounter[7:4];
			BSC[3:0] = combinedCounter[3:0];
			if (reset)
				begin
					charReceived = 1'b0;
					SRclk = 1'b0;
					combinedCounter = 8'b0;
				end
			else if (enable)
				begin
					charReceived = 1'b0;
					if (combinedCounter[3:0] == 4'b0111) // BSC Middle of the bit
						SRclk = 1'b1; 
					else // (4'b0111 != BSC)
						SRclk = 1'b0;
					if((combinedCounter[7:4] == 4'b1001) & (combinedCounter[3:0] == 4'b1111))
						charReceived = 1'b1;
					combinedCounter = combinedCounter + 8'b1;
				end
			else // !enable
				begin
					SRclk = 1'b0;
					if (combinedCounter[7:4] == 4'b1001)
						begin
							charReceived = 1'b1;
							combinedCounter = 8'b0;
						end
					else // 4'b1001 != BIC
						begin
							charReceived = 1'b0;
						end			
				end
			//default: combinedCounter = 8'bx;
		end
endmodule

VnCcode/startBit.v
/*
Bryan Bednarski
EE 371 Prof. Peckol Winter 2016
Project 3: Extending a Microprocessor

startBit.v
This verilog module determines when to enable the Bit Sample Counter and 
Bit Indentification Counters for the Serial In Parallel Out Modules
*/

module startBit(enable, clk, reset, bitStream, BIC, BSC);
	output	reg	enable;
	input  		clk, reset, bitStream;
	input [3:0]	BIC, BSC;
	reg 		ns;
	
	// State encoding
	parameter DISABLE = 1'b0, ENABLE = 1'b1;
	
	always@(*) begin
		case (enable)
			DISABLE: if ((BIC == 4'b0000) && bitStream == 0) // Start bit of character (start bit)
						ns = ENABLE;
					else
						ns = DISABLE;
			ENABLE: if ((BIC == 4'b1001) && (BSC == 4'b1111) && bitStream == 1) 
					// Will turn the enable off when at the end of the last bit in sequence
						ns = DISABLE;
					else
						ns = ENABLE;
		endcase
	end
	
	always@(posedge clk) begin
		if (reset)
			enable <= DISABLE;
		else
			enable <= ns;
	end
endmodule

VnCcode/SIPO.v
/*	Joanna Mazer
	EE 371 Peckol Winter 2016
	Project 3: Extending a Microprocessor
	SIPO.v
	
	This verilog module functions as a serial in, parallel out
	shift register. As individual data bits are entered into 
	the system, the 10 bit output will shift once to the left
	accordingly.
*/


module SIPO(data_out, clk, reset, data_in); // Serial In -> Parallel Out (10 bits)

	input 			clk, reset;
	input 			data_in;
	output [9:0] 	data_out;

	reg [9:0] 		Q;
	reg 			load;

	assign data_out = Q; 
	
	always @(posedge clk or posedge reset) begin
		if (reset) 
			begin
				Q <= 10'b0;
			end
		else 
			begin // Shifts bits down in sequence. module holds 10 bits at a time
				Q[0] <= data_in;
				Q[1] <= Q[0];
				Q[2] <= Q[1];
				Q[3] <= Q[2];
				Q[4] <= Q[3];
				Q[5] <= Q[4];
				Q[6] <= Q[5];
				Q[7] <= Q[6];
				Q[8] <= Q[7];
				Q[9] <= Q[8];
			end
	end
endmodule 
	
/* 	always @(posedge clk or posedge reset) begin
		if (reset) 
			begin
				Q <= 10'b0000000000;
				count <= 3'b000;
			end
		else 
			begin
				if (count == 3'b111)
					begin   	// 8 bits from data_in
						load <= 1'b1;				// load enabled
						count <= 3'b000;			
					end
				else 
					begin 
						load <= 1'b0;
						count <= count + 1; 	   	// counting 8 bits from data_in
						Q[0] <= data_in;
						Q[1] <= Q[0];
						Q[2] <= Q[1];
						Q[3] <= Q[2];
						Q[4] <= Q[3];
						Q[5] <= Q[4];
						Q[6] <= Q[5];
						Q[7] <= Q[6];
						Q[8] <= Q[7];
						Q[9] <= Q[8];
					end
			end
	end
	
	assign data_out = Q; 

endmodule 

 */

VnCcode/serial_buffer.v
/*	Joanna Mazer
	EE 371 Peckol Winter 2016
	Project 3: Extending a Microprocessor
	serial_buffer.v
	
	This verilog module functions as a simple buffer
	to provide additional signal integrity to the serial 
	input and to the serial output of the system.
*/

module serial_buffer (clk, reset, data_in, data_out);
	input 	clk, reset, data_in;
	output 	data_out; 

	reg Q;

	always @(posedge clk or posedge reset) begin
		if (reset) begin
			Q <= 1'b0;			
		end
		else begin
			Q <= data_in;
		end
	end

	assign data_out = Q; 

endmodule

VnCcode/receiving.v
/*	Joanna Mazer
	EE 371 Peckol Winter 2016
	Project 3: Extending a Microprocessor
	receiving.v
	
	This module combines the sub-modules SIPO.v, startBit.v, 
	characterBitCount.v and serial_buffer.v to simplify the
	inputs and outputs of the system.
*/

`include "serial_buffer.v"
`include "SIPO.v"
`include "startBit.v"
`include "characterBitCount.v"

module receiving (clk, reset, data_in, data_out);

	input 			clk, reset, data_in;
	output [9:0] 	data_out;
	output  		charReceived;

	wire 		buffer_out, enable, characterReceived;
	wire [9:0] 	SR_out;
	wire [3:0] 	bitID, bitSample;

	serial_buffer 		input_buffer	(clk, reset, data_in, buffer_out);
	SIPO 				shift_register 	(SR_out, SRclk, reset, buffer_out);
	startBit			start_bit		(enable, clk, reset, buffer_out, bitID, bitSample); 
	characterBitCount	cBitCount 		(characterReceived, SRclk, bitID, bitSample, clk, reset, bitStream, enable);

	assign data_out = SR_out;
	assign charReceived = characterReceived;

endmodule

VnCcode/receiving_testbench.v
/*	Joanna Mazer
	EE 371 Peckol Winter 2016
	Project 3: Extending a Microprocessor
	receiving_testbench.v
	
	These modules function as the testbench to the receiving.v file.
	A truth table will be generated, as well as a gtkwave output
	waveform.
*/

`include "receiving.v"

module receiving_testbench;
	// connect the two modules
	wire 		clk, reset, data_in;
	wire [9:0] 	data_out;
	wire 	 	charReceived;
	
	// declare an instance of the module
	receiving receiving_test(clk, reset, data_in, data_out);

	// declare an instance of the Tester module
	Tester test1(clk, reset, data_in, data_out);
	
	// file specifications for gtkwave
	initial
		begin
		// dump file is for dumping all the variables in a simulation
		$dumpfile("receiving.vcd");
		
		// dumps all the variables in module myDesign and below
		// but not modules instantiated in myDesign into the dump file.
		$dumpvars(1, receiving_test);
		end

endmodule

module Tester (clk, reset, data_in, data_out);

	input [9:0] data_out;
	input 		charReceived;
	output reg 	clk, reset, data_in;

	
	parameter stimDelay = 10;
	
	initial begin 
		$display("\t\t clk reset data_in \t data_out \t Time");
		$monitor("\t %b \t %b \t %b \t %b \t %b", clk, reset, data_in, data_out, charReceived, $time);
	end
	
	always #stimDelay clk = ~clk;
	
	initial begin // Stimulus 
		#(2*stimDelay) clk = 1'b0; reset = 1'b0; data_in = 1'b1; // (no data)
		#(2*stimDelay) reset = 1'b1;	// (reset)
		#(2*stimDelay) reset = 1'b0;
		#(32*stimDelay) data_in = 1'b1;
		#(32*stimDelay) data_in = 1'b1;
		#(32*stimDelay) data_in = 1'b0;	// (start bit) INPUT SIGNAL: (msb) 0110100101 (lsb)
		//#(16*stimDelay);
		#(32*stimDelay) data_in = 1'b1;	// (start of data)
		//#(16*stimDelay);
		#(32*stimDelay) data_in = 1'b1;
		//#(16*stimDelay);
		#(32*stimDelay) data_in = 1'b0;
		//#(16*stimDelay);
		#(32*stimDelay) data_in = 1'b1;
		//#(16*stimDelay);
		#(32*stimDelay) data_in = 1'b0;
		//#(16*stimDelay);
		#(32*stimDelay) data_in = 1'b0;
		//#(16*stimDelay);
		#(32*stimDelay) data_in = 1'b1;	// (end of data)
		//#(16*stimDelay);
		#(32*stimDelay) data_in = 1'b0;	// (parity bit)
		//#(16*stimDelay);
		#(32*stimDelay) data_in = 1'b1;	// (end bit)
		#(32*stimDelay);
		// #(2*stimDelay) data_in = 1'b1;	// (no data)
		// #(32*stimDelay);
		// #(2*stimDelay) data_in = 1'b1;	
		// #(32*stimDelay);
		// #(2*stimDelay) data_in = 1'b1;
		// #(32*stimDelay);
		// #(2*stimDelay) data_in = 1'b1;
		// #(32*stimDelay);

		$finish; 						// finish simulation
	end

endmodule

VnCcode/receiving.vcd
$date
	Sun Feb 21 19:13:37 2016
$end
$version
	Icarus Verilog
$end
$timescale
	1s
$end
$scope module receiving_testbench $end
$scope module receiving_test $end
$var wire 10 ! SR_out [9:0] $end
$var wire 1 " SRclk $end
$var wire 4 # bitID [3:0] $end
$var wire 4 $ bitSample [3:0] $end
$var wire 1 % bitStream $end
$var wire 1 & buffer_out $end
$var wire 1 ' charReceived $end
$var wire 1 ( characterReceived $end
$var wire 1 ) clk $end
$var wire 1 * data_in $end
$var wire 10 + data_out [9:0] $end
$var wire 1 , enable $end
$var wire 1 - reset $end
$upscope $end
$upscope $end
$enddefinitions $end
#0
$dumpvars
x-
x,
bx +
x*
x)
0(
0'
x&
z%
b0 $
b0 #
0"
bx !
$end
#20
1&
1*
0-
1)
#30
0)
#40
0,
0&
1)
1-
#50
0)
#60
1,
1&
1)
0-
#70
0)
#80
1)
#90
0)
#100
b1 $
1)
#110
0)
#120
b10 $
1)
#130
0)
#140
b11 $
1)
#150
0)
#160
b100 $
1)
#170
0)
#180
b101 $
1)
#190
0)
#200
b110 $
1)
#210
0)
#220
bx1 !
bx1 +
1"
b111 $
1)
#230
0)
#240
0"
b1000 $
1)
#250
0)
#260
b1001 $
1)
#270
0)
#280
b1010 $
1)
#290
0)
#300
b1011 $
1)
#310
0)
#320
b1100 $
1)
#330
0)
#340
b1101 $
1)
#350
0)
#360
b1110 $
1)
#370
0)
#380
b1111 $
1)
#390
0)
#400
b0 $
b1 #
1)
#410
0)
#420
b1 $
1)
#430
0)
#440
b10 $
1)
#450
0)
#460
b11 $
1)
#470
0)
#480
b100 $
1)
#490
0)
#500
b101 $
1)
#510
0)
#520
b110 $
1)
#530
0)
#540
bx11 !
bx11 +
1"
b111 $
1)
#550
0)
#560
0"
b1000 $
1)
#570
0)
#580
b1001 $
1)
#590
0)
#600
b1010 $
1)
#610
0)
#620
b1011 $
1)
#630
0)
#640
b1100 $
1)
#650
0)
#660
b1101 $
1)
#670
0)
#680
b1110 $
1)
#690
0)
#700
b1111 $
1)
#710
0)
#720
b0 $
b10 #
1)
#730
0)
#740
b1 $
1)
#750
0)
#760
b10 $
1)
#770
0)
#780
b11 $
1)
#790
0)
#800
b100 $
1)
#810
0)
#820
b101 $
1)
#830
0)
#840
b110 $
1)
#850
0)
#860
bx111 !
bx111 +
1"
b111 $
1)
#870
0)
#880
0"
b1000 $
1)
#890
0)
#900
b1001 $
1)
#910
0)
#920
b1010 $
1)
#930
0)
#940
b1011 $
1)
#950
0)
#960
b1100 $
1)
#970
0)
#980
b1101 $
1)
#990
0)
#1000
b1110 $
1)
#1010
0)
#1020
0&
b1111 $
1)
0*
#1030
0)
#1040
b0 $
b11 #
1)
#1050
0)
#1060
b1 $
1)
#1070
0)
#1080
b10 $
1)
#1090
0)
#1100
b11 $
1)
#1110
0)
#1120
b100 $
1)
#1130
0)
#1140
b101 $
1)
#1150
0)
#1160
b110 $
1)
#1170
0)
#1180
bx1110 !
bx1110 +
1"
b111 $
1)
#1190
0)
#1200
0"
b1000 $
1)
#1210
0)
#1220
b1001 $
1)
#1230
0)
#1240
b1010 $
1)
#1250
0)
#1260
b1011 $
1)
#1270
0)
#1280
b1100 $
1)
#1290
0)
#1300
b1101 $
1)
#1310
0)
#1320
b1110 $
1)
#1330
0)
#1340
1&
b1111 $
1)
1*
#1350
0)
#1360
b0 $
b100 #
1)
#1370
0)
#1380
b1 $
1)
#1390
0)
#1400
b10 $
1)
#1410
0)
#1420
b11 $
1)
#1430
0)
#1440
b100 $
1)
#1450
0)
#1460
b101 $
1)
#1470
0)
#1480
b110 $
1)
#1490
0)
#1500
bx11101 !
bx11101 +
1"
b111 $
1)
#1510
0)
#1520
0"
b1000 $
1)
#1530
0)
#1540
b1001 $
1)
#1550
0)
#1560
b1010 $
1)
#1570
0)
#1580
b1011 $
1)
#1590
0)
#1600
b1100 $
1)
#1610
0)
#1620
b1101 $
1)
#1630
0)
#1640
b1110 $
1)
#1650
0)
#1660
b1111 $
1)
#1670
0)
#1680
b0 $
b101 #
1)
#1690
0)
#1700
b1 $
1)
#1710
0)
#1720
b10 $
1)
#1730
0)
#1740
b11 $
1)
#1750
0)
#1760
b100 $
1)
#1770
0)
#1780
b101 $
1)
#1790
0)
#1800
b110 $
1)
#1810
0)
#1820
bx111011 !
bx111011 +
1"
b111 $
1)
#1830
0)
#1840
0"
b1000 $
1)
#1850
0)
#1860
b1001 $
1)
#1870
0)
#1880
b1010 $
1)
#1890
0)
#1900
b1011 $
1)
#1910
0)
#1920
b1100 $
1)
#1930
0)
#1940
b1101 $
1)
#1950
0)
#1960
b1110 $
1)
#1970
0)
#1980
0&
b1111 $
1)
0*
#1990
0)
#2000
b0 $
b110 #
1)
#2010
0)
#2020
b1 $
1)
#2030
0)
#2040
b10 $
1)
#2050
0)
#2060
b11 $
1)
#2070
0)
#2080
b100 $
1)
#2090
0)
#2100
b101 $
1)
#2110
0)
#2120
b110 $
1)
#2130
0)
#2140
bx1110110 !
bx1110110 +
1"
b111 $
1)
#2150
0)
#2160
0"
b1000 $
1)
#2170
0)
#2180
b1001 $
1)
#2190
0)
#2200
b1010 $
1)
#2210
0)
#2220
b1011 $
1)
#2230
0)
#2240
b1100 $
1)
#2250
0)
#2260
b1101 $
1)
#2270
0)
#2280
b1110 $
1)
#2290
0)
#2300
1&
b1111 $
1)
1*
#2310
0)
#2320
b0 $
b111 #
1)
#2330
0)
#2340
b1 $
1)
#2350
0)
#2360
b10 $
1)
#2370
0)
#2380
b11 $
1)
#2390
0)
#2400
b100 $
1)
#2410
0)
#2420
b101 $
1)
#2430
0)
#2440
b110 $
1)
#2450
0)
#2460
bx11101101 !
bx11101101 +
1"
b111 $
1)
#2470
0)
#2480
0"
b1000 $
1)
#2490
0)
#2500
b1001 $
1)
#2510
0)
#2520
b1010 $
1)
#2530
0)
#2540
b1011 $
1)
#2550
0)
#2560
b1100 $
1)
#2570
0)
#2580
b1101 $
1)
#2590
0)
#2600
b1110 $
1)
#2610
0)
#2620
0&
b1111 $
1)
0*
#2630
0)
#2640
b0 $
b1000 #
1)
#2650
0)
#2660
b1 $
1)
#2670
0)
#2680
b10 $
1)
#2690
0)
#2700
b11 $
1)
#2710
0)
#2720
b100 $
1)
#2730
0)
#2740
b101 $
1)
#2750
0)
#2760
b110 $
1)
#2770
0)
#2780
bx111011010 !
bx111011010 +
1"
b111 $
1)
#2790
0)
#2800
0"
b1000 $
1)
#2810
0)
#2820
b1001 $
1)
#2830
0)
#2840
b1010 $
1)
#2850
0)
#2860
b1011 $
1)
#2870
0)
#2880
b1100 $
1)
#2890
0)
#2900
b1101 $
1)
#2910
0)
#2920
b1110 $
1)
#2930
0)
#2940
b1111 $
1)
#2950
0)
#2960
b0 $
b1001 #
1)
#2970
0)
#2980
b1 $
1)
#2990
0)
#3000
b10 $
1)
#3010
0)
#3020
b11 $
1)
#3030
0)
#3040
b100 $
1)
#3050
0)
#3060
b101 $
1)
#3070
0)
#3080
b110 $
1)
#3090
0)
#3100
b1110110100 !
b1110110100 +
1"
b111 $
1)
#3110
0)
#3120
0"
b1000 $
1)
#3130
0)
#3140
b1001 $
1)
#3150
0)
#3160
b1010 $
1)
#3170
0)
#3180
b1011 $
1)
#3190
0)
#3200
b1100 $
1)
#3210
0)
#3220
b1101 $
1)
#3230
0)
#3240
b1110 $
1)
#3250
0)
#3260
1&
1(
1'
b1111 $
1)
1*
#3270
0)
#3280
0,
0(
0'
b0 $
b1010 #
1)
#3290
0)
#3300
b1 $
1)
#3310
0)
#3320
1)
#3330
0)
#3340
1)
#3350
0)
#3360
1)
#3370
0)
#3380
1)
#3390
0)
#3400
1)
#3410
0)
#3420
1)
#3430
0)
#3440
1)
#3450
0)
#3460
1)
#3470
0)
#3480
1)
#3490
0)
#3500
1)
#3510
0)
#3520
1)
#3530
0)
#3540
1)
#3550
0)
#3560
1)
#3570
0)
#3580
0&
1)
0*
#3590
0)
#3600
1)
#3610
0)
#3620
1)
#3630
0)
#3640
1)
#3650
0)
#3660
1)
#3670
0)
#3680
1)
#3690
0)
#3700
1)
#3710
0)
#3720
1)
#3730
0)
#3740
1)
#3750
0)
#3760
1)
#3770
0)
#3780
1)
#3790
0)
#3800
1)
#3810
0)
#3820
1)
#3830
0)
#3840
1)
#3850
0)
#3860
1)
#3870
0)
#3880
1)
#3890
0)
#3900
1&
1)
1*
